appartme_paas/__init__.py
appartme_paas/client.py
appartme_paas/const.py
appartme_paas/exceptions.py
appartme_paas-0.1.2.dist-info/LICENSE
appartme_paas-0.1.2.dist-info/METADATA
appartme_paas-0.1.2.dist-info/WHEEL
appartme_paas-0.1.2.dist-info/top_level.txt
appartme_paas-0.1.2.dist-info/RECORD
